topsis/__init__.py
topsis/__main__.py
topsis_prabhnoor_102003560-1.0.1.dist-info/LICENSE.txt
topsis_prabhnoor_102003560-1.0.1.dist-info/METADATA
topsis_prabhnoor_102003560-1.0.1.dist-info/WHEEL
topsis_prabhnoor_102003560-1.0.1.dist-info/entry_points.txt
topsis_prabhnoor_102003560-1.0.1.dist-info/top_level.txt
topsis_prabhnoor_102003560-1.0.1.dist-info/RECORD
