Metadata-Version: 2.1
Name: topsis-prabhnoor-102003560
Version: 1.0.1
Summary: A Python package to find TOPSIS for multi-criteria decision analysis method
Home-page: https://github.com/Prabhnoor500/topsis_python_package
Author: Prabhnoor Singh Ghotra
Author-email: psingh1_be20@thapar.edu
License: MIT
Keywords: UCS654,TIET
Classifier: Development Status :: 3 - Alpha
Classifier: Intended Audience :: Developers
Classifier: Operating System :: Microsoft :: Windows :: Windows 10
Classifier: License :: OSI Approved :: MIT License
Classifier: Programming Language :: Python :: 3
License-File: LICENSE.txt
Requires-Dist: pandas
Requires-Dist: tabulate
